[{"name":"Cacafean","code":"012813014","cityCode":"012813000"},{"name":"Daquioag","code":"012813005","cityCode":"012813000"},{"name":"Elizabeth","code":"012813004","cityCode":"012813000"},{"name":"Escoda","code":"012813006","cityCode":"012813000"},{"name":"Ferdinand","code":"012813007","cityCode":"012813000"},{"name":"Fortuna","code":"012813008","cityCode":"012813000"},{"name":"Imelda","code":"012813003","cityCode":"012813000"},{"name":"Lydia (Pob.)","code":"012813009","cityCode":"012813000"},{"name":"Mabuti","code":"012813010","cityCode":"012813000"},{"name":"Pacifico","code":"012813001","cityCode":"012813000"},{"name":"Santiago","code":"012813013","cityCode":"012813000"},{"name":"Tabucbuc","code":"012813012","cityCode":"012813000"},{"name":"Valdez","code":"012813011","cityCode":"012813000"}]