[{"name":"Binalayangan","code":"012928001","cityCode":"012928000"},{"name":"Binongan","code":"012928002","cityCode":"012928000"},{"name":"Borobor","code":"012928003","cityCode":"012928000"},{"name":"Cabaritan","code":"012928004","cityCode":"012928000"},{"name":"Cabigbigaan","code":"012928005","cityCode":"012928000"},{"name":"Calautit","code":"012928006","cityCode":"012928000"},{"name":"Calay-ab","code":"012928007","cityCode":"012928000"},{"name":"Camestizoan","code":"012928008","cityCode":"012928000"},{"name":"Casili","code":"012928009","cityCode":"012928000"},{"name":"Flora","code":"012928010","cityCode":"012928000"},{"name":"Lagatit","code":"012928011","cityCode":"012928000"},{"name":"Laoingen","code":"012928012","cityCode":"012928000"},{"name":"Lussoc","code":"012928013","cityCode":"012928000"},{"name":"Nagbettedan","code":"012928015","cityCode":"012928000"},{"name":"Naglaoa-an","code":"012928016","cityCode":"012928000"},{"name":"Nalasin","code":"012928014","cityCode":"012928000"},{"name":"Nambaran","code":"012928017","cityCode":"012928000"},{"name":"Nanerman","code":"012928018","cityCode":"012928000"},{"name":"Napo","code":"012928019","cityCode":"012928000"},{"name":"Padu Chico","code":"012928020","cityCode":"012928000"},{"name":"Padu Grande","code":"012928021","cityCode":"012928000"},{"name":"Paguraper","code":"012928022","cityCode":"012928000"},{"name":"Panay","code":"012928023","cityCode":"012928000"},{"name":"Pangpangdan","code":"012928024","cityCode":"012928000"},{"name":"Parada","code":"012928025","cityCode":"012928000"},{"name":"Paras","code":"012928026","cityCode":"012928000"},{"name":"Poblacion","code":"012928027","cityCode":"012928000"},{"name":"Puerta Real","code":"012928030","cityCode":"012928000"},{"name":"Pussuac","code":"012928031","cityCode":"012928000"},{"name":"Quimmarayan","code":"012928032","cityCode":"012928000"},{"name":"San Pablo","code":"012928033","cityCode":"012928000"},{"name":"Santa Cruz","code":"012928034","cityCode":"012928000"},{"name":"Santo Tomas","code":"012928035","cityCode":"012928000"},{"name":"Sived","code":"012928036","cityCode":"012928000"},{"name":"Suksukit","code":"012928039","cityCode":"012928000"},{"name":"Vacunero","code":"012928038","cityCode":"012928000"}]