[{"name":"Ambonao","code":"015517001","cityCode":"015517000"},{"name":"Ambuetel","code":"015517002","cityCode":"015517000"},{"name":"Banaoang","code":"015517003","cityCode":"015517000"},{"name":"Bued","code":"015517004","cityCode":"015517000"},{"name":"Buenlag","code":"015517005","cityCode":"015517000"},{"name":"Cabilocaan","code":"015517006","cityCode":"015517000"},{"name":"Dinalaoan","code":"015517007","cityCode":"015517000"},{"name":"Doyong","code":"015517008","cityCode":"015517000"},{"name":"Gabon","code":"015517009","cityCode":"015517000"},{"name":"Lasip","code":"015517010","cityCode":"015517000"},{"name":"Longos","code":"015517011","cityCode":"015517000"},{"name":"Lumbang","code":"015517012","cityCode":"015517000"},{"name":"Macabito","code":"015517013","cityCode":"015517000"},{"name":"Malabago","code":"015517014","cityCode":"015517000"},{"name":"Mancup","code":"015517015","cityCode":"015517000"},{"name":"Nagsaing","code":"015517016","cityCode":"015517000"},{"name":"Nalsian","code":"015517017","cityCode":"015517000"},{"name":"Poblacion East","code":"015517018","cityCode":"015517000"},{"name":"Poblacion West","code":"015517019","cityCode":"015517000"},{"name":"Quesban","code":"015517020","cityCode":"015517000"},{"name":"San Miguel","code":"015517022","cityCode":"015517000"},{"name":"San Vicente","code":"015517023","cityCode":"015517000"},{"name":"Songkoy","code":"015517024","cityCode":"015517000"},{"name":"Talibaew","code":"015517025","cityCode":"015517000"}]