[{"name":"Abra","code":"021513001","cityCode":"021513000"},{"name":"Aguiguican","code":"021513005","cityCode":"021513000"},{"name":"Bangatan Ngagan","code":"021513006","cityCode":"021513000"},{"name":"Baracaoit","code":"021513007","cityCode":"021513000"},{"name":"Baraoidan","code":"021513008","cityCode":"021513000"},{"name":"Barbarit","code":"021513009","cityCode":"021513000"},{"name":"Basao","code":"021513010","cityCode":"021513000"},{"name":"Bolos Point","code":"021513056","cityCode":"021513000"},{"name":"Cabayu","code":"021513011","cityCode":"021513000"},{"name":"Calaoagan Bassit","code":"021513012","cityCode":"021513000"},{"name":"Calaoagan Dackel","code":"021513013","cityCode":"021513000"},{"name":"Capiddigan","code":"021513014","cityCode":"021513000"},{"name":"Capissayan Norte","code":"021513015","cityCode":"021513000"},{"name":"Capissayan Sur","code":"021513016","cityCode":"021513000"},{"name":"Casicallan Norte","code":"021513019","cityCode":"021513000"},{"name":"Casicallan Sur","code":"021513018","cityCode":"021513000"},{"name":"Centro Norte (Pob.)","code":"021513020","cityCode":"021513000"},{"name":"Centro Sur (Pob.)","code":"021513021","cityCode":"021513000"},{"name":"Cullit","code":"021513022","cityCode":"021513000"},{"name":"Cumao","code":"021513023","cityCode":"021513000"},{"name":"Cunig","code":"021513024","cityCode":"021513000"},{"name":"Dummun","code":"021513025","cityCode":"021513000"},{"name":"Fugu","code":"021513026","cityCode":"021513000"},{"name":"Ganzano","code":"021513027","cityCode":"021513000"},{"name":"Guising","code":"021513028","cityCode":"021513000"},{"name":"L. Adviento","code":"021513031","cityCode":"021513000"},{"name":"Langgan","code":"021513029","cityCode":"021513000"},{"name":"Lapogan","code":"021513030","cityCode":"021513000"},{"name":"Mabuno","code":"021513033","cityCode":"021513000"},{"name":"Nabaccayan","code":"021513035","cityCode":"021513000"},{"name":"Naddungan","code":"021513036","cityCode":"021513000"},{"name":"Nagatutuan","code":"021513037","cityCode":"021513000"},{"name":"Nassiping","code":"021513038","cityCode":"021513000"},{"name":"Newagac","code":"021513039","cityCode":"021513000"},{"name":"Palagao Norte","code":"021513040","cityCode":"021513000"},{"name":"Palagao Sur","code":"021513041","cityCode":"021513000"},{"name":"Piña Este","code":"021513042","cityCode":"021513000"},{"name":"Piña Weste","code":"021513043","cityCode":"021513000"},{"name":"San Carlos","code":"021513057","cityCode":"021513000"},{"name":"San Vicente","code":"021513044","cityCode":"021513000"},{"name":"Santa Maria","code":"021513045","cityCode":"021513000"},{"name":"Sidem","code":"021513046","cityCode":"021513000"},{"name":"Sta. Ana","code":"021513047","cityCode":"021513000"},{"name":"T. Elizaga","code":"021513052","cityCode":"021513000"},{"name":"Tagumay","code":"021513048","cityCode":"021513000"},{"name":"Takiki","code":"021513049","cityCode":"021513000"},{"name":"Taligan","code":"021513050","cityCode":"021513000"},{"name":"Tanglagan","code":"021513051","cityCode":"021513000"},{"name":"Tubungan Este","code":"021513053","cityCode":"021513000"},{"name":"Tubungan Weste","code":"021513054","cityCode":"021513000"}]