[{"name":"Barangay I (Pob.)","code":"034913001","cityCode":"034913000"},{"name":"Barangay II (Pob.)","code":"034913002","cityCode":"034913000"},{"name":"Barangay III (Pob.)","code":"034913003","cityCode":"034913000"},{"name":"Barangay IV (Pob.)","code":"034913004","cityCode":"034913000"},{"name":"Betania","code":"034913005","cityCode":"034913000"},{"name":"Canantong","code":"034913006","cityCode":"034913000"},{"name":"Nauzon","code":"034913009","cityCode":"034913000"},{"name":"Pangarulong","code":"034913011","cityCode":"034913000"},{"name":"Pinagbayanan","code":"034913013","cityCode":"034913000"},{"name":"Sagana","code":"034913016","cityCode":"034913000"},{"name":"San Felipe","code":"034913023","cityCode":"034913000"},{"name":"San Fernando","code":"034913017","cityCode":"034913000"},{"name":"San Isidro","code":"034913018","cityCode":"034913000"},{"name":"San Josef","code":"034913019","cityCode":"034913000"},{"name":"San Juan","code":"034913020","cityCode":"034913000"},{"name":"San Vicente","code":"034913021","cityCode":"034913000"},{"name":"Siclong","code":"034913022","cityCode":"034913000"}]