[{"name":"Adya","code":"041014001","cityCode":"041014000"},{"name":"Anilao","code":"041014003","cityCode":"041014000"},{"name":"Anilao-Labac","code":"041014004","cityCode":"041014000"},{"name":"Antipolo Del Norte","code":"041014005","cityCode":"041014000"},{"name":"Antipolo Del Sur","code":"041014006","cityCode":"041014000"},{"name":"Bagong Pook","code":"041014007","cityCode":"041014000"},{"name":"Balintawak","code":"041014009","cityCode":"041014000"},{"name":"Banaybanay","code":"041014010","cityCode":"041014000"},{"name":"Barangay 12 (Pob.)","code":"041014077","cityCode":"041014000"},{"name":"Bolbok","code":"041014011","cityCode":"041014000"},{"name":"Bugtong na Pulo","code":"041014012","cityCode":"041014000"},{"name":"Bulacnin","code":"041014013","cityCode":"041014000"},{"name":"Bulaklakan","code":"041014014","cityCode":"041014000"},{"name":"Calamias","code":"041014015","cityCode":"041014000"},{"name":"Cumba","code":"041014016","cityCode":"041014000"},{"name":"Dagatan","code":"041014017","cityCode":"041014000"},{"name":"Duhatan","code":"041014018","cityCode":"041014000"},{"name":"Halang","code":"041014020","cityCode":"041014000"},{"name":"Inosloban","code":"041014021","cityCode":"041014000"},{"name":"Kayumanggi","code":"041014022","cityCode":"041014000"},{"name":"Latag","code":"041014024","cityCode":"041014000"},{"name":"Lodlod","code":"041014025","cityCode":"041014000"},{"name":"Lumbang","code":"041014026","cityCode":"041014000"},{"name":"Mabini","code":"041014027","cityCode":"041014000"},{"name":"Malagonlong","code":"041014028","cityCode":"041014000"},{"name":"Malitlit","code":"041014029","cityCode":"041014000"},{"name":"Marauoy","code":"041014030","cityCode":"041014000"},{"name":"Mataas Na Lupa","code":"041014031","cityCode":"041014000"},{"name":"Munting Pulo","code":"041014032","cityCode":"041014000"},{"name":"Pagolingin Bata","code":"041014033","cityCode":"041014000"},{"name":"Pagolingin East","code":"041014034","cityCode":"041014000"},{"name":"Pagolingin West","code":"041014035","cityCode":"041014000"},{"name":"Pangao","code":"041014036","cityCode":"041014000"},{"name":"Pinagkawitan","code":"041014037","cityCode":"041014000"},{"name":"Pinagtongulan","code":"041014038","cityCode":"041014000"},{"name":"Plaridel","code":"041014039","cityCode":"041014000"},{"name":"Poblacion Barangay 1","code":"041014040","cityCode":"041014000"},{"name":"Poblacion Barangay 10","code":"041014041","cityCode":"041014000"},{"name":"Poblacion Barangay 11","code":"041014042","cityCode":"041014000"},{"name":"Poblacion Barangay 2","code":"041014043","cityCode":"041014000"},{"name":"Poblacion Barangay 3","code":"041014044","cityCode":"041014000"},{"name":"Poblacion Barangay 4","code":"041014045","cityCode":"041014000"},{"name":"Poblacion Barangay 5","code":"041014046","cityCode":"041014000"},{"name":"Poblacion Barangay 6","code":"041014047","cityCode":"041014000"},{"name":"Poblacion Barangay 7","code":"041014048","cityCode":"041014000"},{"name":"Poblacion Barangay 8","code":"041014049","cityCode":"041014000"},{"name":"Poblacion Barangay 9","code":"041014050","cityCode":"041014000"},{"name":"Poblacion Barangay 9-A","code":"041014076","cityCode":"041014000"},{"name":"Pusil","code":"041014051","cityCode":"041014000"},{"name":"Quezon","code":"041014052","cityCode":"041014000"},{"name":"Rizal","code":"041014053","cityCode":"041014000"},{"name":"Sabang","code":"041014054","cityCode":"041014000"},{"name":"Sampaguita","code":"041014055","cityCode":"041014000"},{"name":"San Benito","code":"041014056","cityCode":"041014000"},{"name":"San Carlos","code":"041014057","cityCode":"041014000"},{"name":"San Celestino","code":"041014058","cityCode":"041014000"},{"name":"San Francisco","code":"041014059","cityCode":"041014000"},{"name":"San Guillermo","code":"041014060","cityCode":"041014000"},{"name":"San Jose","code":"041014061","cityCode":"041014000"},{"name":"San Lucas","code":"041014062","cityCode":"041014000"},{"name":"San Salvador","code":"041014063","cityCode":"041014000"},{"name":"San Sebastian","code":"041014008","cityCode":"041014000"},{"name":"Santo Niño","code":"041014068","cityCode":"041014000"},{"name":"Santo Toribio","code":"041014069","cityCode":"041014000"},{"name":"Sapac","code":"041014064","cityCode":"041014000"},{"name":"Sico","code":"041014066","cityCode":"041014000"},{"name":"Talisay","code":"041014070","cityCode":"041014000"},{"name":"Tambo","code":"041014071","cityCode":"041014000"},{"name":"Tangob","code":"041014072","cityCode":"041014000"},{"name":"Tanguay","code":"041014073","cityCode":"041014000"},{"name":"Tibig","code":"041014074","cityCode":"041014000"},{"name":"Tipacan","code":"041014075","cityCode":"041014000"}]