[{"name":"Anak-Dagat","code":"041012001","cityCode":"041012000"},{"name":"Arumahan","code":"041012002","cityCode":"041012000"},{"name":"Ayao-iyao","code":"041012003","cityCode":"041012000"},{"name":"Bagong Pook","code":"041012004","cityCode":"041012000"},{"name":"Bagong Sikat","code":"041012005","cityCode":"041012000"},{"name":"Balanga","code":"041012006","cityCode":"041012000"},{"name":"Bukal","code":"041012007","cityCode":"041012000"},{"name":"Cahilan I","code":"041012009","cityCode":"041012000"},{"name":"Cahilan II","code":"041012010","cityCode":"041012000"},{"name":"Dayapan","code":"041012011","cityCode":"041012000"},{"name":"District I (Pob.)","code":"041012032","cityCode":"041012000"},{"name":"District II (Pob.)","code":"041012033","cityCode":"041012000"},{"name":"District III (Pob.)","code":"041012034","cityCode":"041012000"},{"name":"District IV (Pob.)","code":"041012035","cityCode":"041012000"},{"name":"Dita","code":"041012012","cityCode":"041012000"},{"name":"Gulod","code":"041012013","cityCode":"041012000"},{"name":"Lucky","code":"041012014","cityCode":"041012000"},{"name":"Maguihan","code":"041012015","cityCode":"041012000"},{"name":"Mahabang Dahilig","code":"041012016","cityCode":"041012000"},{"name":"Mahayahay","code":"041012017","cityCode":"041012000"},{"name":"Maigsing Dahilig","code":"041012018","cityCode":"041012000"},{"name":"Maligaya","code":"041012020","cityCode":"041012000"},{"name":"Malinis","code":"041012021","cityCode":"041012000"},{"name":"Masalisi","code":"041012022","cityCode":"041012000"},{"name":"Mataas Na Bayan","code":"041012023","cityCode":"041012000"},{"name":"Matingain I","code":"041012024","cityCode":"041012000"},{"name":"Matingain II","code":"041012025","cityCode":"041012000"},{"name":"Mayasang","code":"041012026","cityCode":"041012000"},{"name":"Niugan","code":"041012027","cityCode":"041012000"},{"name":"Nonong Casto","code":"041012028","cityCode":"041012000"},{"name":"Palanas","code":"041012029","cityCode":"041012000"},{"name":"Payapa Ibaba","code":"041012030","cityCode":"041012000"},{"name":"Payapa Ilaya","code":"041012031","cityCode":"041012000"},{"name":"Rizal","code":"041012036","cityCode":"041012000"},{"name":"Sambal Ibaba","code":"041012037","cityCode":"041012000"},{"name":"Sambal Ilaya","code":"041012038","cityCode":"041012000"},{"name":"San Isidro Ibaba","code":"041012039","cityCode":"041012000"},{"name":"San Isidro Itaas","code":"041012040","cityCode":"041012000"},{"name":"Sangalang","code":"041012041","cityCode":"041012000"},{"name":"Sinisian East","code":"041012048","cityCode":"041012000"},{"name":"Sinisian West","code":"041012049","cityCode":"041012000"},{"name":"Talaga","code":"041012043","cityCode":"041012000"},{"name":"Tubigan","code":"041012044","cityCode":"041012000"},{"name":"Tubuan","code":"041012045","cityCode":"041012000"},{"name":"Wawa Ibaba","code":"041012046","cityCode":"041012000"},{"name":"Wawa Ilaya","code":"041012047","cityCode":"041012000"}]