[{"name":"Acacia","code":"042118049","cityCode":"042118000"},{"name":"Adlas","code":"042118001","cityCode":"042118000"},{"name":"Anahaw I","code":"042118050","cityCode":"042118000"},{"name":"Anahaw II","code":"042118054","cityCode":"042118000"},{"name":"Balite I","code":"042118003","cityCode":"042118000"},{"name":"Balite II","code":"042118004","cityCode":"042118000"},{"name":"Balubad","code":"042118005","cityCode":"042118000"},{"name":"Banaba","code":"042118055","cityCode":"042118000"},{"name":"Barangay I (Pob.)","code":"042118032","cityCode":"042118000"},{"name":"Barangay II (Pob.)","code":"042118033","cityCode":"042118000"},{"name":"Barangay III (Pob.)","code":"042118034","cityCode":"042118000"},{"name":"Barangay IV (Pob.)","code":"042118035","cityCode":"042118000"},{"name":"Barangay V (Pob.)","code":"042118036","cityCode":"042118000"},{"name":"Batas","code":"042118006","cityCode":"042118000"},{"name":"Biga I","code":"042118007","cityCode":"042118000"},{"name":"Biga II","code":"042118056","cityCode":"042118000"},{"name":"Biluso","code":"042118008","cityCode":"042118000"},{"name":"Bucal","code":"042118010","cityCode":"042118000"},{"name":"Buho","code":"042118009","cityCode":"042118000"},{"name":"Bulihan","code":"042118011","cityCode":"042118000"},{"name":"Cabangaan","code":"042118012","cityCode":"042118000"},{"name":"Carmen","code":"042118013","cityCode":"042118000"},{"name":"Hoyo","code":"042118057","cityCode":"042118000"},{"name":"Hukay","code":"042118014","cityCode":"042118000"},{"name":"Iba","code":"042118015","cityCode":"042118000"},{"name":"Inchican","code":"042118016","cityCode":"042118000"},{"name":"Ipil I","code":"042118051","cityCode":"042118000"},{"name":"Ipil II","code":"042118058","cityCode":"042118000"},{"name":"Kalubkob","code":"042118017","cityCode":"042118000"},{"name":"Kaong","code":"042118018","cityCode":"042118000"},{"name":"Lalaan I","code":"042118019","cityCode":"042118000"},{"name":"Lalaan II","code":"042118020","cityCode":"042118000"},{"name":"Litlit","code":"042118021","cityCode":"042118000"},{"name":"Lucsuhin","code":"042118022","cityCode":"042118000"},{"name":"Lumil","code":"042118023","cityCode":"042118000"},{"name":"Maguyam","code":"042118026","cityCode":"042118000"},{"name":"Malabag","code":"042118027","cityCode":"042118000"},{"name":"Malaking Tatyao","code":"042118059","cityCode":"042118000"},{"name":"Mataas Na Burol","code":"042118028","cityCode":"042118000"},{"name":"Munting Ilog","code":"042118029","cityCode":"042118000"},{"name":"Narra I","code":"042118052","cityCode":"042118000"},{"name":"Narra II","code":"042118060","cityCode":"042118000"},{"name":"Narra III","code":"042118061","cityCode":"042118000"},{"name":"Paligawan","code":"042118030","cityCode":"042118000"},{"name":"Pasong Langka","code":"042118031","cityCode":"042118000"},{"name":"Pooc I","code":"042118037","cityCode":"042118000"},{"name":"Pooc II","code":"042118062","cityCode":"042118000"},{"name":"Pulong Bunga","code":"042118038","cityCode":"042118000"},{"name":"Pulong Saging","code":"042118039","cityCode":"042118000"},{"name":"Puting Kahoy","code":"042118040","cityCode":"042118000"},{"name":"Sabutan","code":"042118041","cityCode":"042118000"},{"name":"San Miguel I","code":"042118042","cityCode":"042118000"},{"name":"San Miguel II","code":"042118063","cityCode":"042118000"},{"name":"San Vicente I","code":"042118043","cityCode":"042118000"},{"name":"San Vicente II","code":"042118064","cityCode":"042118000"},{"name":"Santol","code":"042118044","cityCode":"042118000"},{"name":"Tartaria","code":"042118045","cityCode":"042118000"},{"name":"Tibig","code":"042118046","cityCode":"042118000"},{"name":"Toledo","code":"042118065","cityCode":"042118000"},{"name":"Tubuan I","code":"042118047","cityCode":"042118000"},{"name":"Tubuan II","code":"042118066","cityCode":"042118000"},{"name":"Tubuan III","code":"042118067","cityCode":"042118000"},{"name":"Ulat","code":"042118048","cityCode":"042118000"},{"name":"Yakal","code":"042118053","cityCode":"042118000"}]