[{"name":"Alingaro","code":"042108001","cityCode":"042108000"},{"name":"Arnaldo Pob.","code":"042108030","cityCode":"042108000"},{"name":"Bacao I","code":"042108002","cityCode":"042108000"},{"name":"Bacao II","code":"042108031","cityCode":"042108000"},{"name":"Bagumbayan Pob.","code":"042108007","cityCode":"042108000"},{"name":"Biclatan","code":"042108011","cityCode":"042108000"},{"name":"Buenavista I","code":"042108012","cityCode":"042108000"},{"name":"Buenavista II","code":"042108032","cityCode":"042108000"},{"name":"Buenavista III","code":"042108033","cityCode":"042108000"},{"name":"Corregidor Pob.","code":"042108013","cityCode":"042108000"},{"name":"Dulong Bayan Pob.","code":"042108005","cityCode":"042108000"},{"name":"Gov. Ferrer Pob.","code":"042108003","cityCode":"042108000"},{"name":"Javalera","code":"042108014","cityCode":"042108000"},{"name":"Manggahan","code":"042108015","cityCode":"042108000"},{"name":"Navarro","code":"042108016","cityCode":"042108000"},{"name":"Ninety Sixth Pob.","code":"042108009","cityCode":"042108000"},{"name":"Panungyanan","code":"042108017","cityCode":"042108000"},{"name":"Pasong Camachile I","code":"042108018","cityCode":"042108000"},{"name":"Pasong Camachile II","code":"042108034","cityCode":"042108000"},{"name":"Pasong Kawayan I","code":"042108020","cityCode":"042108000"},{"name":"Pasong Kawayan II","code":"042108021","cityCode":"042108000"},{"name":"Pinagtipunan","code":"042108022","cityCode":"042108000"},{"name":"Prinza Pob.","code":"042108010","cityCode":"042108000"},{"name":"Sampalucan Pob.","code":"042108004","cityCode":"042108000"},{"name":"San Francisco","code":"042108023","cityCode":"042108000"},{"name":"San Gabriel Pob.","code":"042108006","cityCode":"042108000"},{"name":"San Juan I","code":"042108025","cityCode":"042108000"},{"name":"San Juan II","code":"042108035","cityCode":"042108000"},{"name":"Santa Clara","code":"042108026","cityCode":"042108000"},{"name":"Santiago","code":"042108027","cityCode":"042108000"},{"name":"Tapia","code":"042108028","cityCode":"042108000"},{"name":"Tejero","code":"042108029","cityCode":"042108000"},{"name":"Vibora Pob.","code":"042108008","cityCode":"042108000"}]