[{"name":"Atisan","code":"043424080","cityCode":"043424000"},{"name":"Bagong Bayan II-A (Pob.)","code":"043424001","cityCode":"043424000"},{"name":"Bagong Pook VI-C (Pob.)","code":"043424002","cityCode":"043424000"},{"name":"Barangay I-A (Pob.)","code":"043424003","cityCode":"043424000"},{"name":"Barangay I-B (Pob.)","code":"043424004","cityCode":"043424000"},{"name":"Barangay II-A (Pob.)","code":"043424005","cityCode":"043424000"},{"name":"Barangay II-B (Pob.)","code":"043424006","cityCode":"043424000"},{"name":"Barangay II-C (Pob.)","code":"043424007","cityCode":"043424000"},{"name":"Barangay II-D (Pob.)","code":"043424008","cityCode":"043424000"},{"name":"Barangay II-E (Pob.)","code":"043424009","cityCode":"043424000"},{"name":"Barangay II-F (Pob.)","code":"043424010","cityCode":"043424000"},{"name":"Barangay III-A (Pob.)","code":"043424011","cityCode":"043424000"},{"name":"Barangay III-B (Pob.)","code":"043424012","cityCode":"043424000"},{"name":"Barangay III-C (Pob.)","code":"043424013","cityCode":"043424000"},{"name":"Barangay III-D (Pob.)","code":"043424014","cityCode":"043424000"},{"name":"Barangay III-E (Pob.)","code":"043424015","cityCode":"043424000"},{"name":"Barangay III-F (Pob.)","code":"043424016","cityCode":"043424000"},{"name":"Barangay IV-A (Pob.)","code":"043424017","cityCode":"043424000"},{"name":"Barangay IV-B (Pob.)","code":"043424018","cityCode":"043424000"},{"name":"Barangay IV-C (Pob.)","code":"043424019","cityCode":"043424000"},{"name":"Barangay V-A (Pob.)","code":"043424020","cityCode":"043424000"},{"name":"Barangay V-B (Pob.)","code":"043424021","cityCode":"043424000"},{"name":"Barangay V-C (Pob.)","code":"043424022","cityCode":"043424000"},{"name":"Barangay V-D (Pob.)","code":"043424023","cityCode":"043424000"},{"name":"Barangay VI-A (Pob.)","code":"043424024","cityCode":"043424000"},{"name":"Barangay VI-B (Pob.)","code":"043424025","cityCode":"043424000"},{"name":"Barangay VI-D (Pob.)","code":"043424027","cityCode":"043424000"},{"name":"Barangay VI-E (Pob.)","code":"043424028","cityCode":"043424000"},{"name":"Barangay VII-A (Pob.)","code":"043424029","cityCode":"043424000"},{"name":"Barangay VII-B (Pob.)","code":"043424030","cityCode":"043424000"},{"name":"Barangay VII-C (Pob.)","code":"043424031","cityCode":"043424000"},{"name":"Barangay VII-D (Pob.)","code":"043424032","cityCode":"043424000"},{"name":"Barangay VII-E (Pob.)","code":"043424033","cityCode":"043424000"},{"name":"Bautista","code":"043424034","cityCode":"043424000"},{"name":"Concepcion","code":"043424035","cityCode":"043424000"},{"name":"Del Remedio","code":"043424036","cityCode":"043424000"},{"name":"Dolores","code":"043424037","cityCode":"043424000"},{"name":"San Antonio 1","code":"043424040","cityCode":"043424000"},{"name":"San Antonio 2","code":"043424041","cityCode":"043424000"},{"name":"San Bartolome","code":"043424042","cityCode":"043424000"},{"name":"San Buenaventura","code":"043424043","cityCode":"043424000"},{"name":"San Crispin","code":"043424044","cityCode":"043424000"},{"name":"San Cristobal","code":"043424045","cityCode":"043424000"},{"name":"San Diego","code":"043424046","cityCode":"043424000"},{"name":"San Francisco","code":"043424047","cityCode":"043424000"},{"name":"San Gabriel","code":"043424048","cityCode":"043424000"},{"name":"San Gregorio","code":"043424049","cityCode":"043424000"},{"name":"San Ignacio","code":"043424050","cityCode":"043424000"},{"name":"San Isidro","code":"043424051","cityCode":"043424000"},{"name":"San Joaquin","code":"043424052","cityCode":"043424000"},{"name":"San Jose","code":"043424053","cityCode":"043424000"},{"name":"San Juan","code":"043424054","cityCode":"043424000"},{"name":"San Lorenzo","code":"043424055","cityCode":"043424000"},{"name":"San Lucas 1","code":"043424056","cityCode":"043424000"},{"name":"San Lucas 2","code":"043424057","cityCode":"043424000"},{"name":"San Marcos","code":"043424058","cityCode":"043424000"},{"name":"San Mateo","code":"043424059","cityCode":"043424000"},{"name":"San Miguel","code":"043424060","cityCode":"043424000"},{"name":"San Nicolas","code":"043424061","cityCode":"043424000"},{"name":"San Pedro","code":"043424062","cityCode":"043424000"},{"name":"San Rafael","code":"043424063","cityCode":"043424000"},{"name":"San Roque","code":"043424064","cityCode":"043424000"},{"name":"San Vicente","code":"043424065","cityCode":"043424000"},{"name":"Santa Ana","code":"043424066","cityCode":"043424000"},{"name":"Santa Catalina","code":"043424067","cityCode":"043424000"},{"name":"Santa Cruz","code":"043424068","cityCode":"043424000"},{"name":"Santa Elena","code":"043424081","cityCode":"043424000"},{"name":"Santa Felomina","code":"043424069","cityCode":"043424000"},{"name":"Santa Isabel","code":"043424070","cityCode":"043424000"},{"name":"Santa Maria","code":"043424082","cityCode":"043424000"},{"name":"Santa Maria Magdalena","code":"043424071","cityCode":"043424000"},{"name":"Santa Monica","code":"043424083","cityCode":"043424000"},{"name":"Santa Veronica","code":"043424072","cityCode":"043424000"},{"name":"Santiago I","code":"043424073","cityCode":"043424000"},{"name":"Santiago II","code":"043424074","cityCode":"043424000"},{"name":"Santisimo Rosario","code":"043424075","cityCode":"043424000"},{"name":"Santo Angel","code":"043424076","cityCode":"043424000"},{"name":"Santo Cristo","code":"043424077","cityCode":"043424000"},{"name":"Santo Niño","code":"043424078","cityCode":"043424000"},{"name":"Soledad","code":"043424079","cityCode":"043424000"}]