[{"name":"Aplaya","code":"043428001","cityCode":"043428000"},{"name":"Balibago","code":"043428002","cityCode":"043428000"},{"name":"Caingin","code":"043428003","cityCode":"043428000"},{"name":"Dila","code":"043428004","cityCode":"043428000"},{"name":"Dita","code":"043428005","cityCode":"043428000"},{"name":"Don Jose","code":"043428006","cityCode":"043428000"},{"name":"Ibaba","code":"043428007","cityCode":"043428000"},{"name":"Kanluran (Pob.)","code":"043428015","cityCode":"043428000"},{"name":"Labas","code":"043428008","cityCode":"043428000"},{"name":"Macabling","code":"043428009","cityCode":"043428000"},{"name":"Malitlit","code":"043428010","cityCode":"043428000"},{"name":"Malusak (Pob.)","code":"043428011","cityCode":"043428000"},{"name":"Market Area (Pob.)","code":"043428012","cityCode":"043428000"},{"name":"Pook","code":"043428016","cityCode":"043428000"},{"name":"Pulong Santa Cruz","code":"043428018","cityCode":"043428000"},{"name":"Santo Domingo","code":"043428020","cityCode":"043428000"},{"name":"Sinalhan","code":"043428022","cityCode":"043428000"},{"name":"Tagapo","code":"043428023","cityCode":"043428000"}]