[{"name":"Basiad","code":"051610001","cityCode":"051610000"},{"name":"Bulala","code":"051610002","cityCode":"051610000"},{"name":"Don Tomas","code":"051610011","cityCode":"051610000"},{"name":"Guitol","code":"051610012","cityCode":"051610000"},{"name":"Kabuluan","code":"051610013","cityCode":"051610000"},{"name":"Kagtalaba","code":"051610014","cityCode":"051610000"},{"name":"Maulawin","code":"051610015","cityCode":"051610000"},{"name":"Patag Ibaba","code":"051610016","cityCode":"051610000"},{"name":"Patag Iraya","code":"051610017","cityCode":"051610000"},{"name":"Plaridel","code":"051610018","cityCode":"051610000"},{"name":"Polungguitguit","code":"051610003","cityCode":"051610000"},{"name":"Rizal","code":"051610004","cityCode":"051610000"},{"name":"Salvacion","code":"051610005","cityCode":"051610000"},{"name":"San Lorenzo","code":"051610006","cityCode":"051610000"},{"name":"San Pedro","code":"051610007","cityCode":"051610000"},{"name":"San Vicente","code":"051610008","cityCode":"051610000"},{"name":"Santa Elena (Pob.)","code":"051610009","cityCode":"051610000"},{"name":"Tabugon","code":"051610019","cityCode":"051610000"},{"name":"Villa San Isidro","code":"051610010","cityCode":"051610000"}]