[{"name":"Barangay Poblacion I","code":"056215003","cityCode":"056215000"},{"name":"Barangay Poblacion II","code":"056215004","cityCode":"056215000"},{"name":"Barangay Poblacion III","code":"056215005","cityCode":"056215000"},{"name":"Barangay Poblacion IV","code":"056215006","cityCode":"056215000"},{"name":"La Esperanza","code":"056215001","cityCode":"056215000"},{"name":"Peñafrancia","code":"056215002","cityCode":"056215000"},{"name":"Salvacion","code":"056215007","cityCode":"056215000"},{"name":"San Antonio","code":"056215008","cityCode":"056215000"},{"name":"San Bartolome","code":"056215009","cityCode":"056215000"},{"name":"San Eugenio","code":"056215010","cityCode":"056215000"},{"name":"San Isidro","code":"056215011","cityCode":"056215000"},{"name":"San Rafael","code":"056215012","cityCode":"056215000"},{"name":"San Roque","code":"056215013","cityCode":"056215000"},{"name":"San Sebastian","code":"056215014","cityCode":"056215000"}]