[{"name":"Barangay 1 (Pob.)","code":"064527001","cityCode":"064527000"},{"name":"Barangay 2 (Pob.)","code":"064527002","cityCode":"064527000"},{"name":"Barangay 3 (Pob.)","code":"064527003","cityCode":"064527000"},{"name":"Barangay 4 (Pob.)","code":"064527004","cityCode":"064527000"},{"name":"Barangay 5 (Pob.)","code":"064527005","cityCode":"064527000"},{"name":"Cabadiangan","code":"064527006","cityCode":"064527000"},{"name":"Camindangan","code":"064527007","cityCode":"064527000"},{"name":"Canturay","code":"064527008","cityCode":"064527000"},{"name":"Cartagena","code":"064527009","cityCode":"064527000"},{"name":"Cayhagan","code":"064527010","cityCode":"064527000"},{"name":"Gil Montilla","code":"064527011","cityCode":"064527000"},{"name":"Mambaroto","code":"064527012","cityCode":"064527000"},{"name":"Manlucahoc","code":"064527013","cityCode":"064527000"},{"name":"Maricalum","code":"064527014","cityCode":"064527000"},{"name":"Nabulao","code":"064527015","cityCode":"064527000"},{"name":"Nauhang","code":"064527016","cityCode":"064527000"},{"name":"San Jose","code":"064527017","cityCode":"064527000"}]