[{"name":"Angilan","code":"071204001","cityCode":"071204000"},{"name":"Bantolinao","code":"071204002","cityCode":"071204000"},{"name":"Bicahan","code":"071204003","cityCode":"071204000"},{"name":"Bitaugan","code":"071204004","cityCode":"071204000"},{"name":"Bungahan","code":"071204005","cityCode":"071204000"},{"name":"Can-omay","code":"071204009","cityCode":"071204000"},{"name":"Canlaas","code":"071204007","cityCode":"071204000"},{"name":"Cansibuan","code":"071204008","cityCode":"071204000"},{"name":"Celing","code":"071204010","cityCode":"071204000"},{"name":"Danao","code":"071204011","cityCode":"071204000"},{"name":"Danicop","code":"071204012","cityCode":"071204000"},{"name":"Mag-aso","code":"071204013","cityCode":"071204000"},{"name":"Poblacion","code":"071204014","cityCode":"071204000"},{"name":"Quinapon-an","code":"071204015","cityCode":"071204000"},{"name":"Santo Rosario","code":"071204016","cityCode":"071204000"},{"name":"Tabuan","code":"071204017","cityCode":"071204000"},{"name":"Tagubaas","code":"071204018","cityCode":"071204000"},{"name":"Tupas","code":"071204019","cityCode":"071204000"},{"name":"Ubojan","code":"071204020","cityCode":"071204000"},{"name":"Viga","code":"071204021","cityCode":"071204000"},{"name":"Villa Aurora","code":"071204022","cityCode":"071204000"}]