[{"name":"Aslum","code":"083702001","cityCode":"083702000"},{"name":"Astorga","code":"083702002","cityCode":"083702000"},{"name":"Bato","code":"083702004","cityCode":"083702000"},{"name":"Binongto-an","code":"083702005","cityCode":"083702000"},{"name":"Binotong","code":"083702006","cityCode":"083702000"},{"name":"Blumentritt (Pob.)","code":"083702049","cityCode":"083702000"},{"name":"Bobonon","code":"083702007","cityCode":"083702000"},{"name":"Borseth","code":"083702008","cityCode":"083702000"},{"name":"Buenavista","code":"083702009","cityCode":"083702000"},{"name":"Bugho","code":"083702010","cityCode":"083702000"},{"name":"Buri","code":"083702011","cityCode":"083702000"},{"name":"Cabadsan","code":"083702012","cityCode":"083702000"},{"name":"Calaasan","code":"083702013","cityCode":"083702000"},{"name":"Cambahanon","code":"083702014","cityCode":"083702000"},{"name":"Cambolao","code":"083702015","cityCode":"083702000"},{"name":"Canvertudes","code":"083702016","cityCode":"083702000"},{"name":"Capiz","code":"083702017","cityCode":"083702000"},{"name":"Cavite","code":"083702018","cityCode":"083702000"},{"name":"Cogon","code":"083702019","cityCode":"083702000"},{"name":"Dapdap","code":"083702020","cityCode":"083702000"},{"name":"Divisoria","code":"083702021","cityCode":"083702000"},{"name":"Ekiran","code":"083702022","cityCode":"083702000"},{"name":"Hinapolan","code":"083702023","cityCode":"083702000"},{"name":"Holy Child I (Pob.)","code":"083702050","cityCode":"083702000"},{"name":"Holy Child II (Pob.)","code":"083702051","cityCode":"083702000"},{"name":"Hubang","code":"083702024","cityCode":"083702000"},{"name":"Hupit","code":"083702025","cityCode":"083702000"},{"name":"Langit","code":"083702026","cityCode":"083702000"},{"name":"Lingayon","code":"083702027","cityCode":"083702000"},{"name":"Lourdes","code":"083702028","cityCode":"083702000"},{"name":"Lukay","code":"083702029","cityCode":"083702000"},{"name":"Magsaysay","code":"083702030","cityCode":"083702000"},{"name":"Milagrosa (Pob.)","code":"083702052","cityCode":"083702000"},{"name":"Mudboron","code":"083702031","cityCode":"083702000"},{"name":"P. Barrantes","code":"083702032","cityCode":"083702000"},{"name":"Peñalosa","code":"083702033","cityCode":"083702000"},{"name":"Pepita","code":"083702034","cityCode":"083702000"},{"name":"Salvacion","code":"083702055","cityCode":"083702000"},{"name":"Salvacion Poblacion","code":"083702035","cityCode":"083702000"},{"name":"San Antonio","code":"083702036","cityCode":"083702000"},{"name":"San Antonio Pob.","code":"083702053","cityCode":"083702000"},{"name":"San Diego","code":"083702037","cityCode":"083702000"},{"name":"San Francisco East","code":"083702038","cityCode":"083702000"},{"name":"San Francisco West","code":"083702039","cityCode":"083702000"},{"name":"San Isidro","code":"083702040","cityCode":"083702000"},{"name":"San Pedro","code":"083702041","cityCode":"083702000"},{"name":"San Roque (Pob.)","code":"083702054","cityCode":"083702000"},{"name":"San Vicente","code":"083702042","cityCode":"083702000"},{"name":"Santiago","code":"083702043","cityCode":"083702000"},{"name":"Santo Niño (Pob.)","code":"083702044","cityCode":"083702000"},{"name":"Santol","code":"083702045","cityCode":"083702000"},{"name":"Tabangohay","code":"083702046","cityCode":"083702000"},{"name":"Tombo","code":"083702047","cityCode":"083702000"},{"name":"Veteranos","code":"083702048","cityCode":"083702000"}]