[{"name":"Anastacio","code":"097210001","cityCode":"097210000"},{"name":"Bandera","code":"097210002","cityCode":"097210000"},{"name":"Bethlehem","code":"097210003","cityCode":"097210000"},{"name":"Dangi","code":"097210004","cityCode":"097210000"},{"name":"Dansullan","code":"097210005","cityCode":"097210000"},{"name":"De Venta Perla","code":"097210006","cityCode":"097210000"},{"name":"Guinles","code":"097210007","cityCode":"097210000"},{"name":"Isis","code":"097210008","cityCode":"097210000"},{"name":"Labrador","code":"097210009","cityCode":"097210000"},{"name":"Lapayanbaja","code":"097210010","cityCode":"097210000"},{"name":"Letapan","code":"097210011","cityCode":"097210000"},{"name":"Linabo","code":"097210012","cityCode":"097210000"},{"name":"Lingasad","code":"097210013","cityCode":"097210000"},{"name":"Macleodes","code":"097210014","cityCode":"097210000"},{"name":"Magangon","code":"097210015","cityCode":"097210000"},{"name":"Maligaya","code":"097210016","cityCode":"097210000"},{"name":"Milad","code":"097210017","cityCode":"097210000"},{"name":"New Lebangon","code":"097210018","cityCode":"097210000"},{"name":"New Sicayab","code":"097210019","cityCode":"097210000"},{"name":"Obay","code":"097210020","cityCode":"097210000"},{"name":"Pian","code":"097210021","cityCode":"097210000"},{"name":"Poblacion North","code":"097210030","cityCode":"097210000"},{"name":"Poblacion South","code":"097210022","cityCode":"097210000"},{"name":"San Antonio","code":"097210023","cityCode":"097210000"},{"name":"San Miguel","code":"097210024","cityCode":"097210000"},{"name":"San Pedro","code":"097210025","cityCode":"097210000"},{"name":"Santo Niño","code":"097210026","cityCode":"097210000"},{"name":"Sianib","code":"097210028","cityCode":"097210000"},{"name":"Silawe","code":"097210027","cityCode":"097210000"},{"name":"Villahermosa","code":"097210029","cityCode":"097210000"}]