[{"name":"Bogayo","code":"097311004","cityCode":"097311000"},{"name":"Bolisong","code":"097311005","cityCode":"097311000"},{"name":"Boyugan East","code":"097311008","cityCode":"097311000"},{"name":"Boyugan West","code":"097311009","cityCode":"097311000"},{"name":"Bualan","code":"097311006","cityCode":"097311000"},{"name":"Diplo","code":"097311010","cityCode":"097311000"},{"name":"Gawil","code":"097311013","cityCode":"097311000"},{"name":"Gusom","code":"097311014","cityCode":"097311000"},{"name":"Kitaan Dagat","code":"097311015","cityCode":"097311000"},{"name":"Lantawan","code":"097311029","cityCode":"097311000"},{"name":"Limamawan","code":"097311017","cityCode":"097311000"},{"name":"Mahayahay","code":"097311019","cityCode":"097311000"},{"name":"Pangi","code":"097311020","cityCode":"097311000"},{"name":"Picanan","code":"097311023","cityCode":"097311000"},{"name":"Poblacion","code":"097311022","cityCode":"097311000"},{"name":"Salagmanok","code":"097311024","cityCode":"097311000"},{"name":"Secade","code":"097311026","cityCode":"097311000"},{"name":"Suminalum","code":"097311027","cityCode":"097311000"}]