[{"name":"Alegria","code":"098301001","cityCode":"098301000"},{"name":"Bagong Buhay","code":"098301026","cityCode":"098301000"},{"name":"Bella","code":"098301004","cityCode":"098301000"},{"name":"Calades","code":"098301005","cityCode":"098301000"},{"name":"Concepcion","code":"098301027","cityCode":"098301000"},{"name":"Dawa-dawa","code":"098301006","cityCode":"098301000"},{"name":"Gulayon","code":"098301007","cityCode":"098301000"},{"name":"Ilisan","code":"098301008","cityCode":"098301000"},{"name":"Kapatagan","code":"098301028","cityCode":"098301000"},{"name":"Kauswagan","code":"098301010","cityCode":"098301000"},{"name":"Kawayan","code":"098301009","cityCode":"098301000"},{"name":"La Paz","code":"098301011","cityCode":"098301000"},{"name":"Lambuyogan","code":"098301012","cityCode":"098301000"},{"name":"Lapirawan","code":"098301013","cityCode":"098301000"},{"name":"Litayon","code":"098301014","cityCode":"098301000"},{"name":"Lutiman","code":"098301015","cityCode":"098301000"},{"name":"Milagrosa","code":"098301002","cityCode":"098301000"},{"name":"Naga-naga","code":"098301016","cityCode":"098301000"},{"name":"Pandan-pandan","code":"098301017","cityCode":"098301000"},{"name":"Payongan","code":"098301018","cityCode":"098301000"},{"name":"Poblacion","code":"098301019","cityCode":"098301000"},{"name":"Santa Maria","code":"098301020","cityCode":"098301000"},{"name":"Santo Niño","code":"098301021","cityCode":"098301000"},{"name":"Talaptap","code":"098301022","cityCode":"098301000"},{"name":"Tampalan","code":"098301023","cityCode":"098301000"},{"name":"Tandiong Muslim","code":"098301024","cityCode":"098301000"},{"name":"Timbang-timbang","code":"098301025","cityCode":"098301000"}]