[{"name":"Bagumbayan","code":"112408019","cityCode":"112408000"},{"name":"Baybay","code":"112408002","cityCode":"112408000"},{"name":"Bolton","code":"112408004","cityCode":"112408000"},{"name":"Bulacan","code":"112408005","cityCode":"112408000"},{"name":"Caputian","code":"112408006","cityCode":"112408000"},{"name":"Ibo","code":"112408007","cityCode":"112408000"},{"name":"Kiblagon","code":"112408009","cityCode":"112408000"},{"name":"Lapu-Lapu","code":"112408010","cityCode":"112408000"},{"name":"Mabini","code":"112408011","cityCode":"112408000"},{"name":"New Baclayon","code":"112408014","cityCode":"112408000"},{"name":"Pitu","code":"112408015","cityCode":"112408000"},{"name":"Poblacion","code":"112408016","cityCode":"112408000"},{"name":"Rizal","code":"112408020","cityCode":"112408000"},{"name":"San Isidro","code":"112408021","cityCode":"112408000"},{"name":"Tagansule","code":"112408018","cityCode":"112408000"}]