[{"name":"Aurora","code":"118201016","cityCode":"118201000"},{"name":"Bagongon","code":"118201001","cityCode":"118201000"},{"name":"Gabi","code":"118201002","cityCode":"118201000"},{"name":"Lagab","code":"118201003","cityCode":"118201000"},{"name":"Mangayon","code":"118201004","cityCode":"118201000"},{"name":"Mapaca","code":"118201005","cityCode":"118201000"},{"name":"Maparat","code":"118201006","cityCode":"118201000"},{"name":"New Alegria","code":"118201007","cityCode":"118201000"},{"name":"Ngan","code":"118201008","cityCode":"118201000"},{"name":"Osmeña","code":"118201009","cityCode":"118201000"},{"name":"Panansalan","code":"118201010","cityCode":"118201000"},{"name":"Poblacion","code":"118201011","cityCode":"118201000"},{"name":"San Jose","code":"118201012","cityCode":"118201000"},{"name":"San Miguel","code":"118201013","cityCode":"118201000"},{"name":"Siocon","code":"118201014","cityCode":"118201000"},{"name":"Tamia","code":"118201015","cityCode":"118201000"}]