[{"name":"Antao","code":"166806001","cityCode":"166806000"},{"name":"Cancavan","code":"166806002","cityCode":"166806000"},{"name":"Carmen (Pob.)","code":"166806003","cityCode":"166806000"},{"name":"Esperanza","code":"166806004","cityCode":"166806000"},{"name":"Hinapoyan","code":"166806008","cityCode":"166806000"},{"name":"Puyat","code":"166806005","cityCode":"166806000"},{"name":"San Vicente","code":"166806006","cityCode":"166806000"},{"name":"Santa Cruz","code":"166806007","cityCode":"166806000"}]